amfirst/__init__.py
amfirst/__main__.py
amfirst/speaker.py
amfirst/speakers/__init__.py
amfirst/speakers/antonello.py
amfirst-0.2.0.dist-info/METADATA
amfirst-0.2.0.dist-info/WHEEL
amfirst-0.2.0.dist-info/entry_points.txt
amfirst-0.2.0.dist-info/top_level.txt
amfirst-0.2.0.dist-info/RECORD
